{
	"animations": [
		{
			"offsets": [
				6,
				-5
			],
			"loop": true,
			"fps": 24,
			"anim": "idle",
			"indices": [],
			"name": "idle"
		},
		{
			"loop": true,
			"offsets": [
				3,
				-23
			],
			"anim": "singRIGHT",
			"fps": 24,
			"name": "right",
			"indices": []
		},
		{
			"loop": true,
			"offsets": [
				-16,
				-18
			],
			"anim": "singUP",
			"fps": 24,
			"name": "up",
			"indices": []
		},
		{
			"offsets": [
				5,
				-16
			],
			"loop": true,
			"fps": 24,
			"anim": "singLEFT",
			"indices": [],
			"name": "left"
		},
		{
			"offsets": [
				4,
				-16
			],
			"loop": true,
			"fps": 24,
			"anim": "singDOWN",
			"indices": [],
			"name": "down"
		}
	],
	"no_antialiasing": false,
	"image": "characters/bfrunremaster",
	"position": [
		0,
		220
	],
	"healthicon": "bftele",
	"flip_x": true,
	"healthbar_colors": [
		49,
		176,
		209
	],
	"camera_position": [
		250,
		-110
	],
	"sing_duration": 4,
	"scale": 1.4
}